django_hashers_passlib-0.4.dist-info/DESCRIPTION.rst
django_hashers_passlib-0.4.dist-info/METADATA
django_hashers_passlib-0.4.dist-info/RECORD
django_hashers_passlib-0.4.dist-info/WHEEL
django_hashers_passlib-0.4.dist-info/metadata.json
django_hashers_passlib-0.4.dist-info/top_level.txt
hashers_passlib/__init__.py
hashers_passlib/converters.py
