Metadata-Version: 1.1
Name: django-hashers-passlib
Version: 0.4
Summary: Django hashers using passlib
Home-page: https://github.com/mathiasertl/django-hashers-passlib
Author: Mathias Ertl
Author-email: mati@er.tl
License: GNU General Public License (GPL) v3
Platform: UNKNOWN
Classifier: Development Status :: 6 - Mature
Classifier: Environment :: Other Environment
Classifier: Environment :: Web Environment
Classifier: Intended Audience :: Developers
Classifier: License :: OSI Approved :: GNU General Public License v3 or later (GPLv3+)
Classifier: Operating System :: OS Independent
Classifier: Programming Language :: Python :: 2
Classifier: Programming Language :: Python :: 2.7
Classifier: Programming Language :: Python :: 3
Classifier: Programming Language :: Python :: 3.4
Classifier: Programming Language :: Python :: 3.5
Classifier: Programming Language :: Python :: 3.6
Classifier: Programming Language :: Python
Classifier: Topic :: Internet :: WWW/HTTP
Classifier: Topic :: Software Development :: Libraries :: Python Modules
Classifier: Topic :: System :: Systems Administration :: Authentication/Directory
